src/__init__.py
src/tinygpt.py
tinygpt-0.0.1.dist-info/METADATA
tinygpt-0.0.1.dist-info/WHEEL
tinygpt-0.0.1.dist-info/top_level.txt
tinygpt-0.0.1.dist-info/RECORD
